spaceinator/__init__.py
spaceinator/__main__.py
spaceinator/app.py
spaceinator/utils.py
Spaceinator-1.1.0.dist-info/LICENSE.txt
Spaceinator-1.1.0.dist-info/METADATA
Spaceinator-1.1.0.dist-info/WHEEL
Spaceinator-1.1.0.dist-info/top_level.txt
Spaceinator-1.1.0.dist-info/RECORD
