Metadata-Version: 2.1
Name: Spaceinator
Version: 1.1.0
Summary: A simple application to press the spacebar within a user-specified timeframe.
Home-page: https://gitlab.com/Tagmeh/spaceinator
Author: John
License: gpl-3.0
Keywords: stay logged in
Platform: UNKNOWN
Requires-Python: >=3.7
License-File: LICENSE.txt
